text_overlay_dataset/__init__.py
text_overlay_dataset/bounding_box_tools.py
text_overlay_dataset/text_overlay_dataset.py
text_overlay_dataset/word_wrap.py
text_overlay_dataset-0.1.1.dist-info/LICENSE
text_overlay_dataset-0.1.1.dist-info/METADATA
text_overlay_dataset-0.1.1.dist-info/WHEEL
text_overlay_dataset-0.1.1.dist-info/top_level.txt
text_overlay_dataset-0.1.1.dist-info/RECORD
