Metadata-Version: 2.1
Name: text-overlay-dataset
Version: 0.1.1
Summary: A dataset iterator for PyTorch to combine and overlay text on an image dataset.
Author-email: Joseph Catrambone <me@josephcatrambone.com>
Project-URL: Homepage, https://github.com/JosephCatrambone/PyTorchTextOverlayDataset
Project-URL: Bug Tracker, https://github.com/JosephCatrambone/PyTorchTextOverlayDataset/issues
Classifier: Programming Language :: Python :: 3
Classifier: License :: OSI Approved :: MIT License
Classifier: Operating System :: OS Independent
Requires-Python: >=3.7
License-File: LICENSE
